[
 {
  "Name": "Default",
  "UserID": "Default",
  "SaintQuartz": 0,
  "SaintQuartzFragment": 0,
  "BonusDay": 0,
  "Booster": 0,
  "BoosterUsed": false,
  "DailyCollect": true,
  "LastCollectedNitro": "2019-06-17T15:10:04.8174314+08:00",
  "UsedBooster": "2019-06-17T15:10:04.8174314+08:00"
 },
 {
  "Name": "Nodball",
  "UserID": "358860565533425664",
  "SaintQuartz": 1,
  "SaintQuartzFragment": 0,
  "BonusDay": 1,
  "Booster": 0,
  "BoosterUsed": false,
  "DailyCollect": true,
  "LastCollectedNitro": "2019-06-14T15:37:13.3609371+08:00",
  "UsedBooster": "2019-06-17T15:37:13.3609371+08:00"
 },
 {
  "Name": "Marat",
  "UserID": "147776519085752320",
  "SaintQuartz": 0,
  "SaintQuartzFragment": 10,
  "BonusDay": 2,
  "Booster": 1,
  "BoosterUsed": false,
  "DailyCollect": false,
  "LastCollectedNitro": "2019-06-17T15:40:57.8544941+08:00",
  "UsedBooster": "2019-06-17T15:40:49.0121238+08:00"
 },
 {
  "Name": "Sano Tsugi",
  "UserID": "498523735603544096",
  "SaintQuartz": 9474,
  "SaintQuartzFragment": 1067,
  "BonusDay": 1,
  "Booster": 0,
  "BoosterUsed": false,
  "DailyCollect": false,
  "LastCollectedNitro": "2019-06-14T15:46:13.533525+08:00",
  "UsedBooster": "2019-06-17T15:46:13.533525+08:00"
 },
 {
  "Name": "Mosalsal",
  "UserID": "517077457841684480",
  "SaintQuartz": 2,
  "SaintQuartzFragment": 7,
  "BonusDay": 1,
  "Booster": 0,
  "BoosterUsed": false,
  "DailyCollect": true,
  "LastCollectedNitro": "2019-06-14T15:52:33.5112639+08:00",
  "UsedBooster": "2019-06-17T15:52:33.5112639+08:00"
 },
 {
  "Name": "Nyalter",
  "UserID": "282849041945985026",
  "SaintQuartz": 0,
  "SaintQuartzFragment": 0,
  "BonusDay": 1,
  "Booster": 0,
  "BoosterUsed": false,
  "DailyCollect": true,
  "LastCollectedNitro": "2019-06-14T15:53:25.1835808+08:00",
  "UsedBooster": "2019-06-17T15:53:25.1835808+08:00"
 },
 {
  "Name": "Gao",
  "UserID": "483067956293664768",
  "SaintQuartz": 1,
  "SaintQuartzFragment": 0,
  "BonusDay": 1,
  "Booster": 0,
  "BoosterUsed": false,
  "DailyCollect": true,
  "LastCollectedNitro": "2019-06-14T15:55:05.1356746+08:00",
  "UsedBooster": "2019-06-17T15:55:05.1356746+08:00"
 },
 {
  "Name": "king of storm - dessu",
  "UserID": "333178324153270272",
  "SaintQuartz": 3,
  "SaintQuartzFragment": 8,
  "BonusDay": 2,
  "Booster": 0,
  "BoosterUsed": false,
  "DailyCollect": false,
  "LastCollectedNitro": "2019-06-14T16:13:44.1520918+08:00",
  "UsedBooster": "2019-06-17T16:13:44.1520918+08:00"
 },
 {
  "Name": "DeViiL",
  "UserID": "431459507420397568",
  "SaintQuartz": 1,
  "SaintQuartzFragment": 1,
  "BonusDay": 2,
  "Booster": 0,
  "BoosterUsed": false,
  "DailyCollect": false,
  "LastCollectedNitro": "2019-06-14T16:20:42.1563056+08:00",
  "UsedBooster": "2019-06-17T16:20:42.1563056+08:00"
 },
 {
  "Name": "Emanon",
  "UserID": "395361876646559745",
  "SaintQuartz": 0,
  "SaintQuartzFragment": 1,
  "BonusDay": 0,
  "Booster": 0,
  "BoosterUsed": false,
  "DailyCollect": true,
  "LastCollectedNitro": "2019-06-14T16:53:45.5082448+08:00",
  "UsedBooster": "2019-06-17T16:53:45.5082448+08:00"
 },
 {
  "Name": "Yaku",
  "UserID": "451314202720862208",
  "SaintQuartz": 0,
  "SaintQuartzFragment": 4,
  "BonusDay": 0,
  "Booster": 0,
  "BoosterUsed": false,
  "DailyCollect": true,
  "LastCollectedNitro": "2019-06-14T18:02:34.708415+08:00",
  "UsedBooster": "2019-06-17T18:02:34.708415+08:00"
 },
 {
  "Name": "Arthur",
  "UserID": "366854859791532034",
  "SaintQuartz": 1,
  "SaintQuartzFragment": 3,
  "BonusDay": 1,
  "Booster": 0,
  "BoosterUsed": false,
  "DailyCollect": false,
  "LastCollectedNitro": "2019-06-14T18:08:33.0310328+08:00",
  "UsedBooster": "2019-06-17T18:08:33.0310328+08:00"
 },
 {
  "Name": "Gintoki Sakata (Silver Samurai)",
  "UserID": "312943964087123968",
  "SaintQuartz": 0,
  "SaintQuartzFragment": 0,
  "BonusDay": 0,
  "Booster": 0,
  "BoosterUsed": false,
  "DailyCollect": true,
  "LastCollectedNitro": "2019-06-14T18:23:08.8292727+08:00",
  "UsedBooster": "2019-06-17T18:23:08.8292727+08:00"
 },
 {
  "Name": "phucnguyenpt",
  "UserID": "246497944142872577",
  "SaintQuartz": 0,
  "SaintQuartzFragment": 0,
  "BonusDay": 0,
  "Booster": 0,
  "BoosterUsed": false,
  "DailyCollect": true,
  "LastCollectedNitro": "2019-06-14T18:24:46.6801474+08:00",
  "UsedBooster": "2019-06-17T18:24:46.6801474+08:00"
 },
 {
  "Name": "Archi",
  "UserID": "223042946084110337",
  "SaintQuartz": 1,
  "SaintQuartzFragment": 1,
  "BonusDay": 1,
  "Booster": 0,
  "BoosterUsed": false,
  "DailyCollect": true,
  "LastCollectedNitro": "2019-06-14T18:31:52.0349446+08:00",
  "UsedBooster": "2019-06-17T18:31:52.0349446+08:00"
 },
 {
  "Name": "shawn_scarface",
  "UserID": "311749998834352131",
  "SaintQuartz": 2,
  "SaintQuartzFragment": 0,
  "BonusDay": 2,
  "Booster": 0,
  "BoosterUsed": false,
  "DailyCollect": false,
  "LastCollectedNitro": "2019-06-14T19:12:48.5818808+08:00",
  "UsedBooster": "2019-06-17T19:12:48.5818808+08:00"
 },
 {
  "Name": "OneNightSunomata",
  "UserID": "454717677278068737",
  "SaintQuartz": 1,
  "SaintQuartzFragment": 0,
  "BonusDay": 1,
  "Booster": 0,
  "BoosterUsed": false,
  "DailyCollect": true,
  "LastCollectedNitro": "2019-06-14T20:06:12.096534+08:00",
  "UsedBooster": "2019-06-17T20:06:12.096534+08:00"
 },
 {
  "Name": "Nano",
  "UserID": "211835050910679041",
  "SaintQuartz": 2,
  "SaintQuartzFragment": 0,
  "BonusDay": 1,
  "Booster": 0,
  "BoosterUsed": false,
  "DailyCollect": true,
  "LastCollectedNitro": "2019-06-14T20:07:45.6073549+08:00",
  "UsedBooster": "2019-06-17T20:07:45.6073549+08:00"
 },
 {
  "Name": "Hyperbub",
  "UserID": "361759504422928387",
  "SaintQuartz": 1,
  "SaintQuartzFragment": 0,
  "BonusDay": 1,
  "Booster": 0,
  "BoosterUsed": false,
  "DailyCollect": true,
  "LastCollectedNitro": "2019-06-14T21:29:03.0892552+08:00",
  "UsedBooster": "2019-06-17T21:29:03.0892552+08:00"
 },
 {
  "Name": "Serakym",
  "UserID": "168463327695994880",
  "SaintQuartz": 0,
  "SaintQuartzFragment": 19,
  "BonusDay": 0,
  "Booster": 0,
  "BoosterUsed": false,
  "DailyCollect": true,
  "LastCollectedNitro": "2019-06-15T13:24:56.9589898+08:00",
  "UsedBooster": "2019-06-18T13:24:56.9589898+08:00"
 },
 {
  "Name": "Masa",
  "UserID": "119280597494530048",
  "SaintQuartz": 0,
  "SaintQuartzFragment": 8,
  "BonusDay": 0,
  "Booster": 0,
  "BoosterUsed": false,
  "DailyCollect": true,
  "LastCollectedNitro": "2019-06-15T13:48:30.5827967+08:00",
  "UsedBooster": "2019-06-18T13:48:30.5827967+08:00"
 },
 {
  "Name": "Clayman",
  "UserID": "277293356814696461",
  "SaintQuartz": 1,
  "SaintQuartzFragment": 0,
  "BonusDay": 1,
  "Booster": 0,
  "BoosterUsed": false,
  "DailyCollect": false,
  "LastCollectedNitro": "2019-06-15T14:15:25.5971677+08:00",
  "UsedBooster": "2019-06-18T14:15:25.5971677+08:00"
 },
 {
  "Name": "Starboardhydra9",
  "UserID": "283884060089253889",
  "SaintQuartz": 2,
  "SaintQuartzFragment": 4,
  "BonusDay": 1,
  "Booster": 0,
  "BoosterUsed": false,
  "DailyCollect": false,
  "LastCollectedNitro": "2019-06-15T14:16:36.0880664+08:00",
  "UsedBooster": "2019-06-18T14:16:36.0880664+08:00"
 },
 {
  "Name": "ルナちゃん",
  "UserID": "422435119861727232",
  "SaintQuartz": 2,
  "SaintQuartzFragment": 1,
  "BonusDay": 1,
  "Booster": 0,
  "BoosterUsed": false,
  "DailyCollect": false,
  "LastCollectedNitro": "2019-06-15T15:41:32.6552885+08:00",
  "UsedBooster": "2019-06-18T15:41:32.6552885+08:00"
 },
 {
  "Name": "Nagito",
  "UserID": "416051588629790730",
  "SaintQuartz": 1,
  "SaintQuartzFragment": 0,
  "BonusDay": 1,
  "Booster": 0,
  "BoosterUsed": false,
  "DailyCollect": false,
  "LastCollectedNitro": "2019-06-15T15:42:18.790515+08:00",
  "UsedBooster": "2019-06-18T15:42:18.790515+08:00"
 }
]